invokebilizer/__init__.py
invokebilizer/_version.py
invokebilizer/extensions.py
invokebilizer/v0_13.py
invokebilizer-0.1.0.dist-info/DESCRIPTION.rst
invokebilizer-0.1.0.dist-info/METADATA
invokebilizer-0.1.0.dist-info/RECORD
invokebilizer-0.1.0.dist-info/WHEEL
invokebilizer-0.1.0.dist-info/metadata.json
invokebilizer-0.1.0.dist-info/pbr.json
invokebilizer-0.1.0.dist-info/top_level.txt
invokebilizer-0.1.0.dist-info/zip-safe
