Metadata-Version: 2.0
Name: invokebilizer
Version: 0.1.0
Summary: INVOKE staBILIZER - wrapper lib to work with any invoke version through requested interface
Home-page: https://github.com/mirasrael/pyinokebilizer
Author: Alexander Bondarev
Author-email: alexander.i.bondarev@gmail.com
License: MIT
Platform: any
Classifier: Environment :: Console
Classifier: Intended Audience :: Developers
Classifier: License :: OSI Approved :: MIT License
Classifier: Operating System :: OS Independent
Classifier: Programming Language :: Python
Classifier: Programming Language :: Python :: 2.7
Classifier: Programming Language :: Python :: 3.5
Classifier: Topic :: Software Development :: Libraries :: Python Modules
Requires-Dist: invoke (<0.14,>=0.10)
Requires-Dist: six
